happy_python_logging/__about__.py
happy_python_logging/__init__.py
happy_python_logging/app.py
happy_python_logging/lib/__init__.py
happy_python_logging/lib/filters.py
happy_python_logging/lint/__init__.py
happy_python_logging/lint/core.py
happy_python_logging/lint/flake8.py
happy_python_logging-0.0.5.dist-info/METADATA
happy_python_logging-0.0.5.dist-info/WHEEL
happy_python_logging-0.0.5.dist-info/entry_points.txt
happy_python_logging-0.0.5.dist-info/licenses/LICENSE
happy_python_logging-0.0.5.dist-info/RECORD
