Metadata-Version: 2.4
Name: happy-python-logging
Version: 0.0.5
Summary: Make practical Python logging easy (and developers happy!)
Project-URL: Documentation, https://github.com/ftnext/happy-python-logging#readme
Project-URL: Issues, https://github.com/ftnext/happy-python-logging/issues
Project-URL: Source, https://github.com/ftnext/happy-python-logging
Author-email: ftnext <takuyafjp+develop@gmail.com>
License-Expression: MIT
License-File: LICENSE
Keywords: log,logger,logging
Classifier: Development Status :: 3 - Alpha
Classifier: Intended Audience :: Developers
Classifier: License :: OSI Approved :: MIT License
Classifier: Operating System :: OS Independent
Classifier: Programming Language :: Python
Classifier: Programming Language :: Python :: 3.9
Classifier: Programming Language :: Python :: 3.10
Classifier: Programming Language :: Python :: 3.11
Classifier: Programming Language :: Python :: 3.12
Classifier: Programming Language :: Python :: 3.13
Classifier: Topic :: System :: Logging
Requires-Python: >=3.9
Requires-Dist: typing-extensions
Provides-Extra: flake8
Requires-Dist: flake8; extra == 'flake8'
